sbo/__init__.py
sbo/sbo.py
sbo-1.1.0.dist-info/AUTHORS
sbo-1.1.0.dist-info/LICENSE
sbo-1.1.0.dist-info/METADATA
sbo-1.1.0.dist-info/WHEEL
sbo-1.1.0.dist-info/pbr.json
sbo-1.1.0.dist-info/top_level.txt
sbo-1.1.0.dist-info/RECORD
