Metadata-Version: 2.1
Name: sbo
Version: 1.1.0
Summary: SBO defines an iterative approach to translate points by a most likely distance from a given dataset
Home-page: UNKNOWN
Author: Felix
Author-email: 10831300+flxai@users.noreply.github.com
License: UNKNOWN
Project-URL: Source Code, https://github.com/flxai/soft-brownian-offset
Project-URL: Bug Tracker, https://github.com/flxai/soft-brownian-offset/issues
Project-URL: Documentation, https://soft-brownian-offset.readthedocs.io
Platform: UNKNOWN
Requires-Dist: numpy (>=1.18.4)
Requires-Dist: scikit-learn (>=0.23.1)
Requires-Dist: tqdm (>=4.39.0)
Requires-Dist: pbr (>=5.4.4)
